vena/__init__.py
vena-0.0.1.dist-info/METADATA
vena-0.0.1.dist-info/WHEEL
vena-0.0.1.dist-info/top_level.txt
vena-0.0.1.dist-info/RECORD
