Metadata-Version: 2.4
Name: vena
Version: 0.0.1
Summary: Dummy lock package for vena
Author: AutoPublisher
